telegram_text_splitter/__init__.py
telegram_text_splitter/splitter.py
telegram_text_splitter-0.1.1.dist-info/licenses/LICENSE
telegram_text_splitter-0.1.1.dist-info/METADATA
telegram_text_splitter-0.1.1.dist-info/WHEEL
telegram_text_splitter-0.1.1.dist-info/top_level.txt
telegram_text_splitter-0.1.1.dist-info/RECORD
