Metadata-Version: 2.4
Name: telegram-text-splitter
Version: 0.1.1
Summary: A Python library for splitting long Markdown texts into Telegram-friendly chunks.
Author-email: kobaltgit <kobaltmail@gmail.com>
Project-URL: Homepage, https://github.com/kobaltgit/telegram_text_splitter
Project-URL: Bug Tracker, https://github.com/kobaltgit/telegram_text_splitter/issues
Classifier: Programming Language :: Python :: 3
Classifier: License :: OSI Approved :: MIT License
Classifier: Operating System :: OS Independent
Classifier: Topic :: Communications :: Chat
Classifier: Topic :: Software Development :: Libraries :: Python Modules
Requires-Python: >=3.8
License-File: LICENSE
Provides-Extra: test
Requires-Dist: pytest>=7.0; extra == "test"
Dynamic: license-file
